gym_csgo/__init__.py
gym_csgo/demo/__init__.py
gym_csgo/demo/args.py
gym_csgo/demo/manual.py
gym_csgo/demo/noop.py
gym_csgo/demo/random.py
gym_csgo/envs/__init__.py
gym_csgo/envs/csgo_env.py
gym_csgo/glue/__init__.py
gym_csgo/glue/display.py
gym_csgo/glue/keyboard.py
gym_csgo/glue/mouse.py
gym_csgo/gsi/__init__.py
gym_csgo/gsi/bomb.py
gym_csgo/gsi/gamestate.py
gym_csgo/gsi/map.py
gym_csgo/gsi/phase_countdowns.py
gym_csgo/gsi/player.py
gym_csgo/gsi/provider.py
gym_csgo/gsi/round.py
gym_csgo/gsi/server.py
gym_csgo/launch/__init__.py
gym_csgo/launch/launch.py
gym_csgo/spaces/__init__.py
gym_csgo/spaces/act.py
gym_csgo/spaces/enum.py
gym_csgo/spaces/obs.py
gym_csgo/specs/__init__.py
gym_csgo/specs/args.py
gym_csgo/specs/game_modes.py
gym_csgo/specs/weapon.py
gym_csgo-0.0.4.dist-info/LICENSE
gym_csgo-0.0.4.dist-info/METADATA
gym_csgo-0.0.4.dist-info/WHEEL
gym_csgo-0.0.4.dist-info/top_level.txt
gym_csgo-0.0.4.dist-info/RECORD
