Metadata-Version: 2.1
Name: gym-csgo
Version: 0.0.4
Summary: Counter-Strike: Global Offensive environment for OpenAI Gym on Linux
Home-page: https://github.com/iksnagreb/gym-csgo
Author: Christoph Berganski
License: MIT
Platform: UNKNOWN
Classifier: License :: OSI Approved :: MIT License
Classifier: Programming Language :: Python :: 3
Classifier: Operating System :: POSIX :: Linux
License-File: LICENSE
Requires-Dist: gym
Requires-Dist: mss
Requires-Dist: numpy
Requires-Dist: opencv-python
Requires-Dist: flask
Requires-Dist: pynput
Requires-Dist: pygame
